MANIFEST.in
README.rst
setup.py
Flask_Debug.egg-info/PKG-INFO
Flask_Debug.egg-info/SOURCES.txt
Flask_Debug.egg-info/dependency_links.txt
Flask_Debug.egg-info/not-zip-safe
Flask_Debug.egg-info/requires.txt
Flask_Debug.egg-info/top_level.txt
flask_debug/__init__.py
flask_debug/dbg.py
flask_debug/security.py
flask_debug/templates/flask_debug/base.html
flask_debug/templates/flask_debug/bootstrap_base.html
flask_debug/templates/flask_debug/config.html
flask_debug/templates/flask_debug/reflect.html
flask_debug_plugins/__init__.py
flask_debug_plugins/templates/flask_debug/plugins.html