Metadata-Version: 1.0
Name: Flask-Debug
Version: 0.4.2
Summary: Shows reflection/configuration to aid the development of Flask applications.
Home-page: http://github.com/mbr/flask-debug
Author: Marc Brinkmann
Author-email: git@marcbrinkmann.de
License: MIT
Platform: UNKNOWN
